trtruntime/__init__.py
trtruntime/inference.py
trtruntime-0.1.0.dist-info/METADATA
trtruntime-0.1.0.dist-info/WHEEL
trtruntime-0.1.0.dist-info/top_level.txt
trtruntime-0.1.0.dist-info/RECORD
