Metadata-Version: 2.4
Name: trtruntime
Version: 0.1.0
Summary: A lightweight TensorRT inference runtime for Python, inspired by onnxruntime
Author-email: Mohd Yusuf <yusuf.intelligentedgesystems@gmail.com>
License: MIT
Keywords: deepstream,gstreamer,cli,onnx,automation,ai,artificial intelligence,computer vision,edge ai,intelligent edge,craftifai,intelligent edge systems,ies,nvidia,jetson,inference,opencv,triton inference server,tensorrt,onnxruntime
Requires-Python: >=3.8
Requires-Dist: numpy
Requires-Dist: pycuda
